odoo/addons/website_critical_css/README.rst
odoo/addons/website_critical_css/__init__.py
odoo/addons/website_critical_css/__manifest__.py
odoo/addons/website_critical_css/i18n/website_critical_css.pot
odoo/addons/website_critical_css/models/__init__.py
odoo/addons/website_critical_css/models/ir_qweb.py
odoo/addons/website_critical_css/models/website_page.py
odoo/addons/website_critical_css/readme/CONTRIBUTORS.rst
odoo/addons/website_critical_css/readme/DESCRIPTION.rst
odoo/addons/website_critical_css/readme/ROADMAP.rst
odoo/addons/website_critical_css/readme/USAGE.rst
odoo/addons/website_critical_css/static/description/icon.png
odoo/addons/website_critical_css/static/description/index.html
odoo/addons/website_critical_css/static/src/js/page_properties.js
odoo/addons/website_critical_css/static/src/xml/page_properties.xml
odoo/addons/website_critical_css/views/templates.xml
odoo/addons/website_critical_css/views/website_page.xml
odoo13_addon_website_critical_css-13.0.2.0.1.dist-info/METADATA
odoo13_addon_website_critical_css-13.0.2.0.1.dist-info/WHEEL
odoo13_addon_website_critical_css-13.0.2.0.1.dist-info/top_level.txt
odoo13_addon_website_critical_css-13.0.2.0.1.dist-info/RECORD
